{
  "id": "shopify",
  "name": "Shopify",
  "description": "List or create products, orders, customers, or validate webhooks in Shopify",
  "definition_cid": "reference_templates/servers/definitions/shopify.py",
  "operations": [
    "list_products",
    "get_product",
    "create_product",
    "list_orders",
    "get_order",
    "list_customers",
    "get_customer",
    "create_customer",
    "process_webhook"
  ],
  "secrets": [
    "SHOPIFY_ACCESS_TOKEN",
    "SHOPIFY_STORE_URL",
    "SHOPIFY_WEBHOOK_SECRET"
  ],
  "notes": "Uses Shopify Admin API access token and store URL for API calls. Supports webhook validation with HMAC-SHA256 signatures. Supports dry-run previews for all operations."
}
